CHANGELOG.md
MANIFEST.in
Pipfile
README.md
setup.cfg
setup.py
colab_env/__init__.py
colab_env/handler.py
colab_env.egg-info/PKG-INFO
colab_env.egg-info/SOURCES.txt
colab_env.egg-info/dependency_links.txt
colab_env.egg-info/requires.txt
colab_env.egg-info/top_level.txt