Metadata-Version: 2.1
Name: colab-env
Version: 0.0.1
Summary: Handles environment variables in Google Colab notebooks
Home-page: UNKNOWN
Author: PaddyAlton
Author-email: paddy.alton@apolitical.co
License: UNKNOWN
Download-URL: https://github.com/apolitical/colab-env/archive/v0.0.1.tar.gz
Platform: UNKNOWN
